platformcli
