Metadata-Version: 1.0
Name: wellcome-platform-cli
Version: 0.2.1
Summary: Build tooling for the Wellcome Digital Platform
Home-page: http://github.com/wellcometrust/platform-cli
Author: Wellcome Digital Platform
Author-email: wellcomedigitalplatform@wellcome.ac.uk
License: License :: OSI Approved :: MIT License
Platform: UNKNOWN
